souse/__init__.py
souse/fake_firewall.json
souse/fake_module.py
souse/souse.py
souse/test/N-assign-1.py
souse/test/N-attr-1.py
souse/test/N-attr-2.py
souse/test/N-call-1.py
souse/test/N-call-2.py
souse/test/N-combo-1.py
souse/test/assign-1.py
souse/test/assign-2.py
souse/test/assign-3.py
souse/test/attr-1.py
souse/test/attr-2.py
souse/test/call-1.py
souse/test/call-2.py
souse/test/call-3.py
souse/test/combo-1.py
souse/test/combo-2.py
souse/test/combo-3.py
souse/test/combo-4.py
souse/test/combo-5.py
souse/test/slice-1.py
souse/test/slice-2.py
souse-3.2.2.dist-info/LICENSE
souse-3.2.2.dist-info/METADATA
souse-3.2.2.dist-info/WHEEL
souse-3.2.2.dist-info/entry_points.txt
souse-3.2.2.dist-info/top_level.txt
souse-3.2.2.dist-info/RECORD
