Metadata-Version: 2.1
Name: souse
Version: 3.2.2
Summary: A tool for converting Python source code to opcode(pickle)
Home-page: https://github.com/Macr0phag3/souse
Author: Tr0y
Author-email: macr0phag3@qq.com
Classifier: Programming Language :: Python :: 3.6
Classifier: License :: OSI Approved :: MIT License
Classifier: Operating System :: OS Independent
Requires-Python: >=3.6
License-File: LICENSE
Requires-Dist: colorama
